i2c.sv
`default_nettype none

module ChipInterface (
    input logic clk, rst_n, 
    input logic gp14, gp15, gp16, gp17, gp18, gp19, gp20, gp21, gp22, gp23,
    output logic gp24, gp25, gp26, gp27, 
    output logic [7:0]led
);
    logic posreset;
    // assign posreset = ~rst_n;
    logic [7:0] lever_input;
    assign lever_input = {gp21, gp20, gp19, gp18, gp17, gp16, gp15, gp14};
    I2C_slave dut(.clock(clk), .reset(rst_n), .SDA_in(gp22), 
    .SDA_out(gp27), .SCL(gp26), .wr_up(gp24), .data_in(lever_input), 
    .data_out(led), .writeOK(), .wr_down(), .data_incoming(gp23));

endmodule

module I2C_slave (
    // in every circuit
    input logic clock, reset, 

    // interface with I2C
    input  logic SDA_in, 
    output logic SDA_out,
    input  logic SCL, // We are fast enough, no need to do clock stretching
    output logic wr_up,

    // interface with downstream thread
    input  logic [7:0] data_in, 
    output logic [7:0] data_out,
    output logic writeOK, wr_down
    
    ,input  logic data_incoming
);

    parameter I2C_ADDRESS = 7'h49;

    // ==================================================================
    // ============= Four little FSM for Pattern Detection: =============
    // ==================================================================

    enum logic {SCL0, SCL1} scl_state, scl_nextstate;
    logic scl_rise, scl_fall, scl_high, scl_low;

    enum logic {SDA0, SDA1} sda_state, sda_nextstate;
    logic sda_rise, sda_fall, sda_high, sda_low;

    enum logic {WAIT_START, SDAFALL} start_state, start_nextstate;
    logic i2c_start;

    enum logic {WAIT_STOP, SCLRISE} stop_state, stop_nextstate;
    logic i2c_stop;

    always_comb begin : SCLstate
        scl_rise = 1'b0;
        scl_fall = 1'b0;
        scl_high = 1'b0;
        scl_low  = 1'b0;
        case (scl_state)
            SCL0: begin
                if (SCL) begin
                    scl_rise = 1'b1;
                    scl_high = 1'b1;
                    scl_nextstate = SCL1;
                end
                else begin
                    scl_low = 1'b1;
                    scl_nextstate = SCL0;
                end
            end
            SCL1: begin
                if (~SCL) begin
                    scl_fall = 1'b1;
                    scl_low = 1'b1;
                    scl_nextstate = SCL0;
                end
                else begin
                    scl_high = 1'b1;
                    scl_nextstate = SCL1;
                end
            end
            default: scl_nextstate = SCL0;
        endcase
    end

    always_comb begin : SDAstate
        sda_rise = 1'b0;
        sda_fall = 1'b0;
        sda_high = 1'b0;
        sda_low  = 1'b0;
        case (sda_state)
            SDA0: begin
                if (SDA_in) begin
                    sda_rise = 1'b1;
                    sda_high = 1'b1;
                    sda_nextstate = SDA1;
                end
                else begin
                    sda_low = 1'b1;
                    sda_nextstate = SDA0;
                end
            end
            SDA1: begin
                if (~SDA_in) begin
                    sda_fall = 1'b1;
                    sda_low = 1'b1;
                    sda_nextstate = SDA0;
                end
                else begin
                    sda_high = 1'b1;
                    sda_nextstate = SDA1;
                end
            end
            default: sda_nextstate = SDA0;
        endcase
    end

    always_comb begin : STARTstate
        i2c_start = 1'b0;
        case (start_state)
            WAIT_START: begin
                if (sda_fall && scl_high) begin
                    start_nextstate = SDAFALL;
                end
                else begin
                    start_nextstate = WAIT_START;
                end
            end
            SDAFALL: begin
                if (scl_fall && sda_low) begin
                    i2c_start = 1'b1;
                    start_nextstate = WAIT_START;
                end
                else if (scl_fall && sda_high) begin
                    start_nextstate = WAIT_START;
                end
                else begin
                    start_nextstate = SDAFALL;
                end
            end
            default: start_nextstate = WAIT_START;
        endcase
    end

    always_comb begin : STOPstate
        i2c_stop = 1'b0;
        case (stop_state)
            WAIT_STOP: begin
                if (scl_rise && sda_low) begin
                    stop_nextstate = SCLRISE;
                end
                else begin
                    stop_nextstate = WAIT_STOP;
                end
            end
            SCLRISE: begin
                if (sda_rise & scl_high) begin
                    i2c_stop = 1'b1;
                    stop_nextstate = WAIT_STOP;
                end
                else if (scl_fall) begin
                    stop_nextstate = WAIT_STOP;
                end
                else begin
                    stop_nextstate = SCLRISE;
                end
            end
            default: stop_nextstate = WAIT_STOP;
        endcase
    end

    always_ff @(posedge clock, negedge reset) begin
        if (~reset) begin
            scl_state <= SCL1; // B/c i2c lines were pulled UP, so by default
            sda_state <= SDA1; // they are 1.
            start_state <= WAIT_START;
            stop_state <= WAIT_STOP;
        end
        else begin
            scl_state <= scl_nextstate; // B/c i2c lines were pulled UP, so by default
            sda_state <= sda_nextstate; // they are 1.
            start_state <= start_nextstate;
            stop_state <= stop_nextstate;
        end
    end

    // ====================================================
    // ============= All Submodule Initiation =============
    // ====================================================

    logic sipo_load, sipo_full, sipo_clear;
    logic [7:0] sipo_out;

    SIPO the_sipo (.clock, .reset, .data_in(SDA_in), .clear(sipo_clear), 
                   .load(sipo_load), .out(sipo_out), .full(sipo_full));

    logic store;
    logic [7:0] register_out;

    Register the_reg (.clock, .reset, .in(sipo_out), .out(register_out), 
                      .enable(store));

    logic piso_load, piso_spit, piso_empty;
    logic piso_out;

    PISO the_piso (.clock, .reset, .data_in(data_in), .spit(piso_spit), 
                   .load(piso_load), .out(piso_out), .empty(piso_empty));

    logic is_correct_address;

    assign is_correct_address = sipo_out[7:1] == I2C_ADDRESS;

    logic r1w0;

    assign r1w0 = sipo_out[0];

    logic ack;

    assign SDA_out = ack ? 1'b0 : piso_out;

    assign writeOK = ~wr_down & piso_empty;

    assign piso_load = ~wr_down & data_incoming & piso_empty;

    assign data_out = register_out;
    
    // ====================================================
    // =============== The Main Control FSM ===============
    // ====================================================

    enum logic [3:0] {IDLE, ADDR_RD, WAIT_END, 
                      READ, READ_ACK, READ_PRELD, READ_LOAD, 
                      WRITE, WRITE_ACK, WRITE_PRELD, WRITE_SEND, WRITE_RELEASE} 
                      state, nextstate;

    always_comb begin : main_FSM
        sipo_clear = 1'b0;
        sipo_load = 1'b0;
        ack = 1'b0;
        store = 1'b0;
        wr_down = 1'b0;
        piso_spit = 1'b0;
        wr_up = 1'b0;
        unique case (state)
            IDLE: begin
                if (i2c_start) begin
                    sipo_clear = 1'b1;
                    nextstate = ADDR_RD;
                end
                else begin
                    nextstate = IDLE;
                end
            end
            ADDR_RD: begin
                if (scl_rise && ~sipo_full) begin
                    sipo_load = 1'b1;
                    nextstate = ADDR_RD;
                end
                else if (sipo_full && ~is_correct_address) begin 
                    // we remove scl_rise here since when sipo is full and scl rise, 
                    // we need to pull the ACK line. this will make us run out of 
                    // time for checking address and RW
                    nextstate = WAIT_END;
                end
                else if (sipo_full && is_correct_address && ~r1w0) begin
                    // State READ is withrespect to slave, where i2c signal 
                    // r1w0 is with respect to master. so need to flip this part. 
                    nextstate = READ;
                end
                else if (sipo_full && is_correct_address && r1w0) begin
                    nextstate = WRITE;
                end
                else begin
                    nextstate = ADDR_RD;
                end
            end
            WAIT_END: begin 
                // This state is to made sure that this line don't 
                // hijack the line in the middle of the i2c. 
                if (i2c_stop)
                    nextstate = IDLE;
                else
                    nextstate = WAIT_END;
            end

            /* READ SIDE */

            READ: begin
                if (scl_fall) begin
                    ack = 1'b1;
                    nextstate = READ_ACK;
                end else begin
                    nextstate = READ;
                end
            end
            READ_ACK: begin
                wr_down = 1'b1;
                if (scl_fall) begin
                    sipo_clear = 1'b1;
                    nextstate = READ_PRELD;
                end else begin
                    ack = 1'b1;
                    nextstate = READ_ACK;
                end
            end
            READ_PRELD: begin
                wr_down = 1'b1;
                if (scl_rise) begin
                    sipo_load = 1'b1;
                    nextstate = READ_LOAD;
                end else begin
                    nextstate = READ_PRELD;
                end
            end
            READ_LOAD: begin
                wr_down = 1'b1;
                if (scl_rise && ~sipo_full) begin
                    sipo_load = 1'b1;
                    nextstate = READ_LOAD;
                end
                else if (scl_fall && sipo_full) begin
                    ack = 1'b1;
                    store = 1'b1;
                    nextstate = READ_ACK; 
                    // end of communication, send acknowledgement
                end
                else if (sda_rise && scl_high) begin
                    // sda change value during scl_low. if sda_rise and scl_high
                    nextstate = IDLE;
                end
                else begin
                    nextstate = READ_LOAD;
                end
            end

            /* WRITE SIDE */

            WRITE: begin
                if (scl_fall) begin
                    ack = 1'b1;
                    nextstate = WRITE_ACK;
                end else begin
                    nextstate = WRITE;
                end
            end
            WRITE_ACK: begin
                if (scl_fall) begin
                    piso_spit = 1'b1;
                    wr_up = 1'b1;
                    nextstate = WRITE_PRELD;
                end else begin
                    ack = 1'b1;
                    nextstate = WRITE_ACK;
                end
            end
            WRITE_PRELD: begin
                if (scl_fall) begin
                    piso_spit = 1'b1;
                    wr_up = 1'b1;
                    nextstate = WRITE_SEND;
                end else begin
                    nextstate = WRITE_PRELD;
                end
            end
            WRITE_SEND: begin
                if (scl_fall && ~piso_empty) begin
                    piso_spit = 1'b1;
                    wr_up = 1'b1;
                    nextstate = WRITE_SEND;
                end
                else if (scl_fall && piso_empty) begin
                    nextstate = WRITE_RELEASE;
                end
                else begin
                    nextstate = WRITE_SEND;
                    wr_up = 1'b1; // we need to hold this line. 
                end
            end
            WRITE_RELEASE: begin // this state releases the SDA line
                if (scl_rise && sda_low) begin
                    nextstate = WRITE_PRELD;
                end
                else if (scl_rise && sda_high) begin
                    nextstate = IDLE;
                end
                else begin
                    nextstate = WRITE_RELEASE;
                end
            end

            default: nextstate = IDLE;
        endcase
    end

    always_ff @(posedge clock, negedge reset) begin
        if (~reset)
            state <= IDLE;
        else
            state <= nextstate;
    end

endmodule

module SIPO #(
    parameter SIZE = 8, 
    parameter UNIT = 1
) (
    input  logic [UNIT-1:0] data_in, 
    input  logic            clock, reset, 
    input  logic            clear, load, 
    output logic [SIZE-1:0] out, 
    output logic            full
);

    logic [$clog2(SIZE):0] counter;

    assign full = counter == SIZE;

    always_ff @(posedge clock, negedge reset) begin
        if (~reset) begin
            out <= 'b0;
            counter <= 'b0;
        end
        else begin
            if (clear) begin
                out <= 'b0;
                counter <= 'b0;
            end
            if (load && counter != SIZE) begin
                out <= {out[SIZE-UNIT-1:0], data_in};
                counter <= counter + 'd1;
            end
        end
    end
    
endmodule: SIPO

module PISO(
    input  logic [7:0] data_in, 
    input  logic            clock, reset, 
    input  logic            spit, load, 
    output logic  out, 
    output logic            empty
);

    logic [3:0] counter, counter_plus_1;

    logic [7:0] register;

    assign empty = counter == 8;

    logic shift;
    assign shift = spit && !empty;

    assign counter_plus_1 = counter + 'd1;

    always_ff @(posedge clock, negedge reset) begin: the_piso
        if (~reset) begin
            register <= 'b0;
            counter <= 'd8;
            out <= 'd0;
        end
        else if (load) begin
            register <= data_in;
            counter <= 'd0;
            out <= 'd0;
        end 
        else if (shift) begin
            register <= {register[6:0], 1'd0};
            counter <= counter_plus_1;
            out <= register[7];
        end
    end
    
endmodule

module Register #(
    parameter SIZE = 8
) (
    input  logic [SIZE-1:0] in, 
    output logic [SIZE-1:0] out, 
    input  logic            clock, reset, 
    input  logic            enable
);

    always_ff @(posedge clock, negedge reset) begin
        if (~reset)
            out <= 'b0;
        else if (enable) begin
            out <= in;
        end
    end
    
endmodule

dump.vcd
$version Generated by VerilatedVcd $end
$timescale 1ps $end
 $scope module  $end
  $var wire 1 # clock $end
  $var wire 1 $ reset $end
  $var wire 1 % SDA_in $end
  $var wire 1 & SDA_out $end
  $var wire 1 ' SCL $end
  $var wire 1 ( wr_up $end
  $var wire 8 ) data_in [7:0] $end
  $var wire 8 * data_out [7:0] $end
  $var wire 1 + writeOK $end
  $var wire 1 , wr_down $end
  $var wire 1 - data_incoming $end
  $scope module I2C_slave $end
   $var wire 1 . clock $end
   $var wire 1 / reset $end
   $var wire 1 0 SDA_in $end
   $var wire 1 1 SDA_out $end
   $var wire 1 2 SCL $end
   $var wire 1 3 wr_up $end
   $var wire 8 4 data_in [7:0] $end
   $var wire 8 5 data_out [7:0] $end
   $var wire 1 6 writeOK $end
   $var wire 1 7 wr_down $end
   $var wire 1 8 data_incoming $end
   $var wire 7 r I2C_ADDRESS [6:0] $end
   $var wire 1 9 scl_state $end
   $var wire 1 : scl_nextstate $end
   $var wire 1 ; scl_rise $end
   $var wire 1 < scl_fall $end
   $var wire 1 = scl_high $end
   $var wire 1 > scl_low $end
   $var wire 1 ? sda_state $end
   $var wire 1 @ sda_nextstate $end
   $var wire 1 A sda_rise $end
   $var wire 1 B sda_fall $end
   $var wire 1 C sda_high $end
   $var wire 1 D sda_low $end
   $var wire 1 E start_state $end
   $var wire 1 F start_nextstate $end
   $var wire 1 G i2c_start $end
   $var wire 1 H stop_state $end
   $var wire 1 I stop_nextstate $end
   $var wire 1 J i2c_stop $end
   $var wire 1 K sipo_load $end
   $var wire 1 L sipo_full $end
   $var wire 1 M sipo_clear $end
   $var wire 8 N sipo_out [7:0] $end
   $var wire 1 O store $end
   $var wire 8 P register_out [7:0] $end
   $var wire 1 Q piso_load $end
   $var wire 1 R piso_spit $end
   $var wire 1 S piso_empty $end
   $var wire 1 T piso_out $end
   $var wire 1 U is_correct_address $end
   $var wire 1 V r1w0 $end
   $var wire 1 W ack $end
   $var wire 4 X state [3:0] $end
   $var wire 4 Y nextstate [3:0] $end
   $scope module the_piso $end
    $var wire 8 Z data_in [7:0] $end
    $var wire 1 [ clock $end
    $var wire 1 \ reset $end
    $var wire 1 ] spit $end
    $var wire 1 ^ load $end
    $var wire 1 _ out $end
    $var wire 1 ` empty $end
    $var wire 4 a counter [3:0] $end
    $var wire 4 b counter_plus_1 [3:0] $end
    $var wire 8 c register [7:0] $end
    $var wire 1 d shift $end
   $upscope $end
   $scope module the_reg $end
    $var wire 32 s SIZE [31:0] $end
    $var wire 8 e in [7:0] $end
    $var wire 8 f out [7:0] $end
    $var wire 1 g clock $end
    $var wire 1 h reset $end
    $var wire 1 i enable $end
   $upscope $end
   $scope module the_sipo $end
    $var wire 32 s SIZE [31:0] $end
    $var wire 32 t UNIT [31:0] $end
    $var wire 1 j data_in [0:0] $end
    $var wire 1 k clock $end
    $var wire 1 l reset $end
    $var wire 1 m clear $end
    $var wire 1 n load $end
    $var wire 8 o out [7:0] $end
    $var wire 1 p full $end
    $var wire 4 q counter [3:0] $end
   $upscope $end
  $upscope $end
 $upscope $end
$enddefinitions $end


#0
1#
0$
0%
0&
0'
0(
b00000000 )
b00000000 *
1+
0,
0-
1.
0/
00
01
02
03
b00000000 4
b00000000 5
16
07
08
19
0:
0;
1<
0=
1>
1?
0@
0A
1B
0C
1D
0E
0F
0G
0H
0I
0J
0K
0L
0M
b00000000 N
0O
b00000000 P
0Q
0R
1S
0T
0U
0V
0W
b0000 X
b0000 Y
b00000000 Z
1[
0\
0]
0^
0_
1`
b1000 a
b1001 b
b00000000 c
0d
b00000000 e
b00000000 f
1g
0h
0i
0j
1k
0l
0m
0n
b00000000 o
0p
b0000 q
b1001001 r
b00000000000000000000000000001000 s
b00000000000000000000000000000001 t
#5000
0#
0.
0[
0g
0k
#10000
1#
1.
1[
1g
1k
#15000
0#
0.
0[
0g
0k
#20000
1#
1.
1[
1g
1k
#25000
0#
1$
1%
1'
0.
1/
10
12
1:
0<
1=
0>
1@
0B
1C
0D
0[
1\
0g
1h
1j
0k
1l
#30000
1#
1.
1[
1g
1k
#35000
0#
0%
0.
00
0@
1B
0C
1D
1F
0[
0g
0j
0k
#40000
1#
1.
0?
0B
1E
1[
1g
1k
#45000
0#
0'
0.
02
0:
1<
0=
1>
0F
1G
1M
b0001 Y
0[
0g
0k
1m
#50000
1#
1.
09
0<
0E
0G
0M
b0001 X
1[
1g
1k
0m
#55000
0#
0.
0[
0g
0k
#60000
1#
1.
1[
1g
1k
#65000
0#
0.
0[
0g
0k
#70000
1#
1.
1[
1g
1k
#75000
0#
0.
0[
0g
0k
#80000
1#
1.
1[
1g
1k
#85000
0#
0.
0[
0g
0k
#90000
1#
1.
1[
1g
1k
#95000
0#
1%
0.
10
1@
1A
1C
0D
0[
0g
1j
0k
#100000
1#
1.
1?
0A
1[
1g
1k
#105000
0#
0.
0[
0g
0k
#110000
1#
1.
1[
1g
1k
#115000
0#
1'
0.
12
1:
1;
1=
0>
1K
0[
0g
0k
1n
#120000
1#
1.
19
0;
0K
b00000001 N
1V
1[
b00000001 e
1g
1k
0n
b00000001 o
b0001 q
#125000
0#
0.
0[
0g
0k
#130000
1#
1.
1[
1g
1k
#135000
0#
0.
0[
0g
0k
#140000
1#
1.
1[
1g
1k
#145000
0#
0.
0[
0g
0k
#150000
1#
1.
1[
1g
1k
#155000
0#
0.
0[
0g
0k
#160000
1#
1.
1[
1g
1k
#165000
0#
0'
0.
02
0:
1<
0=
1>
0[
0g
0k
#170000
1#
1.
09
0<
1[
1g
1k
#175000
0#
0.
0[
0g
0k
#180000
1#
1.
1[
1g
1k
#185000
0#
0.
0[
0g
0k
#190000
1#
1.
1[
1g
1k
#195000
0#
0%
0.
00
0@
1B
0C
1D
0[
0g
0j
0k
#200000
1#
1.
0?
0B
1[
1g
1k
#205000
0#
0.
0[
0g
0k
#210000
1#
1.
1[
1g
1k
#215000
0#
1'
0.
12
1:
1;
1=
0>
1I
1K
0[
0g
0k
1n
#220000
1#
1.
19
0;
1H
0K
b00000010 N
0V
1[
b00000010 e
1g
1k
0n
b00000010 o
b0010 q
#225000
0#
0.
0[
0g
0k
#230000
1#
1.
1[
1g
1k
#235000
0#
0.
0[
0g
0k
#240000
1#
1.
1[
1g
1k
#245000
0#
0.
0[
0g
0k
#250000
1#
1.
1[
1g
1k
#255000
0#
0.
0[
0g
0k
#260000
1#
1.
1[
1g
1k
#265000
0#
0'
0.
02
0:
1<
0=
1>
0I
0[
0g
0k
#270000
1#
1.
09
0<
0H
1[
1g
1k
#275000
0#
0.
0[
0g
0k
#280000
1#
1.
1[
1g
1k
#285000
0#
0.
0[
0g
0k
#290000
1#
1.
1[
1g
1k
#295000
0#
0.
0[
0g
0k
#300000
1#
1.
1[
1g
1k
#305000
0#
0.
0[
0g
0k
#310000
1#
1.
1[
1g
1k
#315000
0#
1'
0.
12
1:
1;
1=
0>
1I
1K
0[
0g
0k
1n
#320000
1#
1.
19
0;
1H
0K
b00000100 N
1[
b00000100 e
1g
1k
0n
b00000100 o
b0011 q
#325000
0#
0.
0[
0g
0k
#330000
1#
1.
1[
1g
1k
#335000
0#
0.
0[
0g
0k
#340000
1#
1.
1[
1g
1k
#345000
0#
0.
0[
0g
0k
#350000
1#
1.
1[
1g
1k
#355000
0#
0.
0[
0g
0k
#360000
1#
1.
1[
1g
1k
#365000
0#
0'
0.
02
0:
1<
0=
1>
0I
0[
0g
0k
#370000
1#
1.
09
0<
0H
1[
1g
1k
#375000
0#
0.
0[
0g
0k
#380000
1#
1.
1[
1g
1k
#385000
0#
0.
0[
0g
0k
#390000
1#
1.
1[
1g
1k
#395000
0#
1%
0.
10
1@
1A
1C
0D
0[
0g
1j
0k
#400000
1#
1.
1?
0A
1[
1g
1k
#405000
0#
0.
0[
0g
0k
#410000
1#
1.
1[
1g
1k
#415000
0#
1'
0.
12
1:
1;
1=
0>
1K
0[
0g
0k
1n
#420000
1#
1.
19
0;
0K
b00001001 N
1V
1[
b00001001 e
1g
1k
0n
b00001001 o
b0100 q
#425000
0#
0.
0[
0g
0k
#430000
1#
1.
1[
1g
1k
#435000
0#
0.
0[
0g
0k
#440000
1#
1.
1[
1g
1k
#445000
0#
0.
0[
0g
0k
#450000
1#
1.
1[
1g
1k
#455000
0#
0.
0[
0g
0k
#460000
1#
1.
1[
1g
1k
#465000
0#
0'
0.
02
0:
1<
0=
1>
0[
0g
0k
#470000
1#
1.
09
0<
1[
1g
1k
#475000
0#
0.
0[
0g
0k
#480000
1#
1.
1[
1g
1k
#485000
0#
0.
0[
0g
0k
#490000
1#
1.
1[
1g
1k
#495000
0#
0%
0.
00
0@
1B
0C
1D
0[
0g
0j
0k
#500000
1#
1.
0?
0B
1[
1g
1k
#505000
0#
0.
0[
0g
0k
#510000
1#
1.
1[
1g
1k
#515000
0#
1'
0.
12
1:
1;
1=
0>
1I
1K
0[
0g
0k
1n
#520000
1#
1.
19
0;
1H
0K
b00010010 N
0V
1[
b00010010 e
1g
1k
0n
b00010010 o
b0101 q
#525000
0#
0.
0[
0g
0k
#530000
1#
1.
1[
1g
1k
#535000
0#
0.
0[
0g
0k
#540000
1#
1.
1[
1g
1k
#545000
0#
0.
0[
0g
0k
#550000
1#
1.
1[
1g
1k
#555000
0#
0.
0[
0g
0k
#560000
1#
1.
1[
1g
1k
#565000
0#
0'
0.
02
0:
1<
0=
1>
0I
0[
0g
0k
#570000
1#
1.
09
0<
0H
1[
1g
1k
#575000
0#
0.
0[
0g
0k
#580000
1#
1.
1[
1g
1k
#585000
0#
0.
0[
0g
0k
#590000
1#
1.
1[
1g
1k
#595000
0#
0.
0[
0g
0k
#600000
1#
1.
1[
1g
1k
#605000
0#
0.
0[
0g
0k
#610000
1#
1.
1[
1g
1k
#615000
0#
1'
0.
12
1:
1;
1=
0>
1I
1K
0[
0g
0k
1n
#620000
1#
1.
19
0;
1H
0K
b00100100 N
1[
b00100100 e
1g
1k
0n
b00100100 o
b0110 q
#625000
0#
0.
0[
0g
0k
#630000
1#
1.
1[
1g
1k
#635000
0#
0.
0[
0g
0k
#640000
1#
1.
1[
1g
1k
#645000
0#
0.
0[
0g
0k
#650000
1#
1.
1[
1g
1k
#655000
0#
0.
0[
0g
0k
#660000
1#
1.
1[
1g
1k
#665000
0#
0'
0.
02
0:
1<
0=
1>
0I
0[
0g
0k
#670000
1#
1.
09
0<
0H
1[
1g
1k
#675000
0#
0.
0[
0g
0k
#680000
1#
1.
1[
1g
1k
#685000
0#
0.
0[
0g
0k
#690000
1#
1.
1[
1g
1k
#695000
0#
1%
0.
10
1@
1A
1C
0D
0[
0g
1j
0k
#700000
1#
1.
1?
0A
1[
1g
1k
#705000
0#
0.
0[
0g
0k
#710000
1#
1.
1[
1g
1k
#715000
0#
1'
0.
12
1:
1;
1=
0>
1K
0[
0g
0k
1n
#720000
1#
1.
19
0;
0K
b01001001 N
1V
1[
b01001001 e
1g
1k
0n
b01001001 o
b0111 q
#725000
0#
0.
0[
0g
0k
#730000
1#
1.
1[
1g
1k
#735000
0#
0.
0[
0g
0k
#740000
1#
1.
1[
1g
1k
#745000
0#
0.
0[
0g
0k
#750000
1#
1.
1[
1g
1k
#755000
0#
0.
0[
0g
0k
#760000
1#
1.
1[
1g
1k
#765000
0#
0'
0.
02
0:
1<
0=
1>
0[
0g
0k
#770000
1#
1.
09
0<
1[
1g
1k
#775000
0#
0.
0[
0g
0k
#780000
1#
1.
1[
1g
1k
#785000
0#
0.
0[
0g
0k
#790000
1#
1.
1[
1g
1k
#795000
0#
0%
0.
00
0@
1B
0C
1D
0[
0g
0j
0k
#800000
1#
1.
0?
0B
1[
1g
1k
#805000
0#
0.
0[
0g
0k
#810000
1#
1.
1[
1g
1k
#815000
0#
1'
0.
12
1:
1;
1=
0>
1I
1K
0[
0g
0k
1n
#820000
1#
1.
19
0;
1H
0K
1L
b10010010 N
1U
0V
b0011 Y
1[
b10010010 e
1g
1k
0n
b10010010 o
1p
b1000 q
#825000
0#
0.
0[
0g
0k
#830000
1#
1.
b0011 X
1[
1g
1k
#835000
0#
0.
0[
0g
0k
#840000
1#
1.
1[
1g
1k
#845000
0#
0.
0[
0g
0k
#850000
1#
1.
1[
1g
1k
#855000
0#
0.
0[
0g
0k
#860000
1#
1.
1[
1g
1k
#865000
0#
0'
0.
02
0:
1<
0=
1>
0I
1W
b0100 Y
0[
0g
0k
#870000
1#
0+
1,
1.
06
17
09
0<
0H
b0100 X
1[
1g
1k
#875000
0#
0.
0[
0g
0k
#880000
1#
1.
1[
1g
1k
#885000
0#
0.
0[
0g
0k
#890000
1#
1.
1[
1g
1k
#895000
0#
1%
0.
10
1@
1A
1C
0D
0[
0g
1j
0k
#900000
1#
1.
1?
0A
1[
1g
1k
#905000
0#
0.
0[
0g
0k
#910000
1#
1.
1[
1g
1k
#915000
0#
1'
0.
12
1:
1;
1=
0>
0[
0g
0k
#920000
1#
1.
19
0;
1[
1g
1k
#925000
0#
0.
0[
0g
0k
#930000
1#
1.
1[
1g
1k
#935000
0#
0.
0[
0g
0k
#940000
1#
1.
1[
1g
1k
#945000
0#
0.
0[
0g
0k
#950000
1#
1.
1[
1g
1k
#955000
0#
0.
0[
0g
0k
#960000
1#
1.
1[
1g
1k
#965000
0#
0.
0[
0g
0k
#970000
1#
1.
1[
1g
1k
#975000
0#
0.
0[
0g
0k
#980000
1#
1.
1[
1g
1k
#985000
0#
0.
0[
0g
0k
#990000
1#
1.
1[
1g
1k
#995000
0#
0.
0[
0g
0k
#1000000
1#
1.
1[
1g
1k
#1005000
0#
0.
0[
0g
0k
#1010000
1#
1.
1[
1g
1k
#1015000
0#
0.
0[
0g
0k
#1020000
1#
1.
1[
1g
1k
#1025000
0#
0.
0[
0g
0k
#1030000
1#
1.
1[
1g
1k
#1035000
0#
0'
0.
02
0:
1<
0=
1>
1M
0W
b0101 Y
0[
0g
0k
1m
#1040000
1#
1.
09
0<
0L
0M
b00000000 N
0U
b0101 X
1[
b00000000 e
1g
1k
0m
b00000000 o
0p
b0000 q
#1045000
0#
0.
0[
0g
0k
#1050000
1#
1.
1[
1g
1k
#1055000
0#
0.
0[
0g
0k
#1060000
1#
1.
1[
1g
1k
#1065000
0#
0.
0[
0g
0k
#1070000
1#
1.
1[
1g
1k
#1075000
0#
0.
0[
0g
0k
#1080000
1#
1.
1[
1g
1k
#1085000
0#
1'
0.
12
1:
1;
1=
0>
1K
b0110 Y
0[
0g
0k
1n
#1090000
1#
1.
19
0;
0K
b00000001 N
1V
b0110 X
1[
b00000001 e
1g
1k
0n
b00000001 o
b0001 q
#1095000
0#
0.
0[
0g
0k
#1100000
1#
1.
1[
1g
1k
#1105000
0#
0.
0[
0g
0k
#1110000
1#
1.
1[
1g
1k
#1115000
0#
0.
0[
0g
0k
#1120000
1#
1.
1[
1g
1k
#1125000
0#
0.
0[
0g
0k
#1130000
1#
1.
1[
1g
1k
#1135000
0#
0'
0.
02
0:
1<
0=
1>
0[
0g
0k
#1140000
1#
1.
09
0<
1[
1g
1k
#1145000
0#
0.
0[
0g
0k
#1150000
1#
1.
1[
1g
1k
#1155000
0#
0.
0[
0g
0k
#1160000
1#
1.
1[
1g
1k
#1165000
0#
0.
0[
0g
0k
#1170000
1#
1.
1[
1g
1k
#1175000
0#
0.
0[
0g
0k
#1180000
1#
1.
1[
1g
1k
#1185000
0#
1'
0.
12
1:
1;
1=
0>
1K
0[
0g
0k
1n
#1190000
1#
1.
19
0;
0K
b00000011 N
1[
b00000011 e
1g
1k
0n
b00000011 o
b0010 q
#1195000
0#
0.
0[
0g
0k
#1200000
1#
1.
1[
1g
1k
#1205000
0#
0.
0[
0g
0k
#1210000
1#
1.
1[
1g
1k
#1215000
0#
0.
0[
0g
0k
#1220000
1#
1.
1[
1g
1k
#1225000
0#
0.
0[
0g
0k
#1230000
1#
1.
1[
1g
1k
#1235000
0#
0'
0.
02
0:
1<
0=
1>
0[
0g
0k
#1240000
1#
1.
09
0<
1[
1g
1k
#1245000
0#
0.
0[
0g
0k
#1250000
1#
1.
1[
1g
1k
#1255000
0#
0.
0[
0g
0k
#1260000
1#
1.
1[
1g
1k
#1265000
0#
0%
0.
00
0@
1B
0C
1D
0[
0g
0j
0k
#1270000
1#
1.
0?
0B
1[
1g
1k
#1275000
0#
0.
0[
0g
0k
#1280000
1#
1.
1[
1g
1k
#1285000
0#
1'
0.
12
1:
1;
1=
0>
1I
1K
0[
0g
0k
1n
#1290000
1#
1.
19
0;
1H
0K
b00000110 N
0V
1[
b00000110 e
1g
1k
0n
b00000110 o
b0011 q
#1295000
0#
0.
0[
0g
0k
#1300000
1#
1.
1[
1g
1k
#1305000
0#
0.
0[
0g
0k
#1310000
1#
1.
1[
1g
1k
#1315000
0#
0.
0[
0g
0k
#1320000
1#
1.
1[
1g
1k
#1325000
0#
0.
0[
0g
0k
#1330000
1#
1.
1[
1g
1k
#1335000
0#
0'
0.
02
0:
1<
0=
1>
0I
0[
0g
0k
#1340000
1#
1.
09
0<
0H
1[
1g
1k
#1345000
0#
0.
0[
0g
0k
#1350000
1#
1.
1[
1g
1k
#1355000
0#
0.
0[
0g
0k
#1360000
1#
1.
1[
1g
1k
#1365000
0#
1%
0.
10
1@
1A
1C
0D
0[
0g
1j
0k
#1370000
1#
1.
1?
0A
1[
1g
1k
#1375000
0#
0.
0[
0g
0k
#1380000
1#
1.
1[
1g
1k
#1385000
0#
1'
0.
12
1:
1;
1=
0>
1K
0[
0g
0k
1n
#1390000
1#
1.
19
0;
0K
b00001101 N
1V
1[
b00001101 e
1g
1k
0n
b00001101 o
b0100 q
#1395000
0#
0.
0[
0g
0k
#1400000
1#
1.
1[
1g
1k
#1405000
0#
0.
0[
0g
0k
#1410000
1#
1.
1[
1g
1k
#1415000
0#
0.
0[
0g
0k
#1420000
1#
1.
1[
1g
1k
#1425000
0#
0.
0[
0g
0k
#1430000
1#
1.
1[
1g
1k
#1435000
0#
0'
0.
02
0:
1<
0=
1>
0[
0g
0k
#1440000
1#
1.
09
0<
1[
1g
1k
#1445000
0#
0.
0[
0g
0k
#1450000
1#
1.
1[
1g
1k
#1455000
0#
0.
0[
0g
0k
#1460000
1#
1.
1[
1g
1k
#1465000
0#
0.
0[
0g
0k
#1470000
1#
1.
1[
1g
1k
#1475000
0#
0.
0[
0g
0k
#1480000
1#
1.
1[
1g
1k
#1485000
0#
1'
0.
12
1:
1;
1=
0>
1K
0[
0g
0k
1n
#1490000
1#
1.
19
0;
0K
b00011011 N
1[
b00011011 e
1g
1k
0n
b00011011 o
b0101 q
#1495000
0#
0.
0[
0g
0k
#1500000
1#
1.
1[
1g
1k
#1505000
0#
0.
0[
0g
0k
#1510000
1#
1.
1[
1g
1k
#1515000
0#
0.
0[
0g
0k
#1520000
1#
1.
1[
1g
1k
#1525000
0#
0.
0[
0g
0k
#1530000
1#
1.
1[
1g
1k
#1535000
0#
0'
0.
02
0:
1<
0=
1>
0[
0g
0k
#1540000
1#
1.
09
0<
1[
1g
1k
